{"dependencies":[{"name":"/home/sahil/neoshop/package.json","includedInParent":true,"mtime":1532005572544},{"name":"/home/sahil/neoshop/node_modules/ipld-dag-pb/package.json","includedInParent":true,"mtime":1531925806809},{"name":"cids","loc":{"line":3,"column":20}},{"name":"protons","loc":{"line":4,"column":24}},{"name":"./dag.proto.js","loc":{"line":5,"column":30}},{"name":"./dag-link","loc":{"line":6,"column":24}},{"name":"./dag-node","loc":{"line":7,"column":24}},{"name":"buffer"}],"generated":{"js":"var Buffer = require(\"buffer\").Buffer;\n'use strict';\n\nvar CID = require('cids');\nvar protons = require('protons');\nvar proto = protons(require('./dag.proto.js'));\nvar DAGLink = require('./dag-link');\nvar DAGNode = require('./dag-node');\n\nexports = module.exports;\n\nfunction cid(node, callback) {\n  if (node.multihash) {\n    return callback(null, new CID(node.multihash));\n  }\n  callback(new Error('not valid dagPB node'));\n}\n\nfunction serialize(node, callback) {\n  var serialized = void 0;\n\n  // If the node is not an instance of a DAGNode, the link.hash might be a Base58 encoded string; decode it\n  if (!DAGNode.isDAGNode(node) && node.links) {\n    node.links = node.links.map(function (link) {\n      return DAGLink.isDAGLink(link) ? link : DAGLink.util.createDagLinkFromB58EncodedHash(link);\n    });\n  }\n\n  try {\n    serialized = proto.PBNode.encode(toProtoBuf(node));\n  } catch (err) {\n    return callback(err);\n  }\n\n  callback(null, serialized);\n}\n\nfunction deserialize(data, callback) {\n  var pbn = proto.PBNode.decode(data);\n\n  var links = pbn.Links.map(function (link) {\n    return new DAGLink(link.Name, link.Tsize, link.Hash);\n  });\n\n  var buf = pbn.Data == null ? Buffer.alloc(0) : Buffer.from(pbn.Data);\n\n  DAGNode.create(buf, links, callback);\n}\n\nfunction toProtoBuf(node) {\n  var pbn = {};\n\n  if (node.data && node.data.length > 0) {\n    pbn.Data = node.data;\n  } else {\n    // NOTE: this has to be null in order to match go-ipfs serialization `null !== new Buffer(0)`\n    pbn.Data = null;\n  }\n\n  if (node.links && node.links.length > 0) {\n    pbn.Links = node.links.map(function (link) {\n      return {\n        Hash: link.multihash,\n        Name: link.name,\n        Tsize: link.size\n      };\n    });\n  } else {\n    pbn.Links = null;\n  }\n\n  return pbn;\n}\n\nexports.serialize = serialize;\nexports.deserialize = deserialize;\nexports.cid = cid;","map":{"mappings":[{"generated":{"line":2,"column":0},"source":"../node_modules/ipld-dag-pb/src/util.js","original":{"line":1,"column":0}},{"generated":{"line":4,"column":0},"source":"../node_modules/ipld-dag-pb/src/util.js","original":{"line":3,"column":0}},{"name":"CID","generated":{"line":4,"column":4},"source":"../node_modules/ipld-dag-pb/src/util.js","original":{"line":3,"column":6}},{"name":"require","generated":{"line":4,"column":10},"source":"../node_modules/ipld-dag-pb/src/util.js","original":{"line":3,"column":12}},{"generated":{"line":4,"column":18},"source":"../node_modules/ipld-dag-pb/src/util.js","original":{"line":3,"column":20}},{"generated":{"line":4,"column":24},"source":"../node_modules/ipld-dag-pb/src/util.js","original":{"line":3,"column":12}},{"generated":{"line":4,"column":25},"source":"../node_modules/ipld-dag-pb/src/util.js","original":{"line":3,"column":0}},{"generated":{"line":5,"column":0},"source":"../node_modules/ipld-dag-pb/src/util.js","original":{"line":4,"column":0}},{"name":"protons","generated":{"line":5,"column":4},"source":"../node_modules/ipld-dag-pb/src/util.js","original":{"line":4,"column":6}},{"name":"require","generated":{"line":5,"column":14},"source":"../node_modules/ipld-dag-pb/src/util.js","original":{"line":4,"column":16}},{"generated":{"line":5,"column":22},"source":"../node_modules/ipld-dag-pb/src/util.js","original":{"line":4,"column":24}},{"generated":{"line":5,"column":31},"source":"../node_modules/ipld-dag-pb/src/util.js","original":{"line":4,"column":16}},{"generated":{"line":5,"column":32},"source":"../node_modules/ipld-dag-pb/src/util.js","original":{"line":4,"column":0}},{"generated":{"line":6,"column":0},"source":"../node_modules/ipld-dag-pb/src/util.js","original":{"line":5,"column":0}},{"name":"proto","generated":{"line":6,"column":4},"source":"../node_modules/ipld-dag-pb/src/util.js","original":{"line":5,"column":6}},{"name":"protons","generated":{"line":6,"column":12},"source":"../node_modules/ipld-dag-pb/src/util.js","original":{"line":5,"column":14}},{"name":"require","generated":{"line":6,"column":20},"source":"../node_modules/ipld-dag-pb/src/util.js","original":{"line":5,"column":22}},{"generated":{"line":6,"column":28},"source":"../node_modules/ipld-dag-pb/src/util.js","original":{"line":5,"column":30}},{"generated":{"line":6,"column":44},"source":"../node_modules/ipld-dag-pb/src/util.js","original":{"line":5,"column":22}},{"generated":{"line":6,"column":45},"source":"../node_modules/ipld-dag-pb/src/util.js","original":{"line":5,"column":14}},{"generated":{"line":6,"column":46},"source":"../node_modules/ipld-dag-pb/src/util.js","original":{"line":5,"column":0}},{"generated":{"line":7,"column":0},"source":"../node_modules/ipld-dag-pb/src/util.js","original":{"line":6,"column":0}},{"name":"DAGLink","generated":{"line":7,"column":4},"source":"../node_modules/ipld-dag-pb/src/util.js","original":{"line":6,"column":6}},{"name":"require","generated":{"line":7,"column":14},"source":"../node_modules/ipld-dag-pb/src/util.js","original":{"line":6,"column":16}},{"generated":{"line":7,"column":22},"source":"../node_modules/ipld-dag-pb/src/util.js","original":{"line":6,"column":24}},{"generated":{"line":7,"column":34},"source":"../node_modules/ipld-dag-pb/src/util.js","original":{"line":6,"column":16}},{"generated":{"line":7,"column":35},"source":"../node_modules/ipld-dag-pb/src/util.js","original":{"line":6,"column":0}},{"generated":{"line":8,"column":0},"source":"../node_modules/ipld-dag-pb/src/util.js","original":{"line":7,"column":0}},{"name":"DAGNode","generated":{"line":8,"column":4},"source":"../node_modules/ipld-dag-pb/src/util.js","original":{"line":7,"column":6}},{"name":"require","generated":{"line":8,"column":14},"source":"../node_modules/ipld-dag-pb/src/util.js","original":{"line":7,"column":16}},{"generated":{"line":8,"column":22},"source":"../node_modules/ipld-dag-pb/src/util.js","original":{"line":7,"column":24}},{"generated":{"line":8,"column":34},"source":"../node_modules/ipld-dag-pb/src/util.js","original":{"line":7,"column":16}},{"generated":{"line":8,"column":35},"source":"../node_modules/ipld-dag-pb/src/util.js","original":{"line":7,"column":0}},{"name":"exports","generated":{"line":10,"column":0},"source":"../node_modules/ipld-dag-pb/src/util.js","original":{"line":9,"column":0}},{"name":"module","generated":{"line":10,"column":10},"source":"../node_modules/ipld-dag-pb/src/util.js","original":{"line":9,"column":10}},{"name":"exports","generated":{"line":10,"column":17},"source":"../node_modules/ipld-dag-pb/src/util.js","original":{"line":9,"column":17}},{"generated":{"line":10,"column":24},"source":"../node_modules/ipld-dag-pb/src/util.js","original":{"line":9,"column":0}},{"generated":{"line":12,"column":0},"source":"../node_modules/ipld-dag-pb/src/util.js","original":{"line":11,"column":0}},{"name":"cid","generated":{"line":12,"column":9},"source":"../node_modules/ipld-dag-pb/src/util.js","original":{"line":11,"column":9}},{"generated":{"line":12,"column":12},"source":"../node_modules/ipld-dag-pb/src/util.js","original":{"line":11,"column":0}},{"name":"node","generated":{"line":12,"column":13},"source":"../node_modules/ipld-dag-pb/src/util.js","original":{"line":11,"column":14}},{"generated":{"line":12,"column":17},"source":"../node_modules/ipld-dag-pb/src/util.js","original":{"line":11,"column":0}},{"name":"callback","generated":{"line":12,"column":19},"source":"../node_modules/ipld-dag-pb/src/util.js","original":{"line":11,"column":20}},{"generated":{"line":12,"column":27},"source":"../node_modules/ipld-dag-pb/src/util.js","original":{"line":11,"column":0}},{"generated":{"line":12,"column":29},"source":"../node_modules/ipld-dag-pb/src/util.js","original":{"line":11,"column":30}},{"generated":{"line":13,"column":0},"source":"../node_modules/ipld-dag-pb/src/util.js","original":{"line":12,"column":2}},{"name":"node","generated":{"line":13,"column":6},"source":"../node_modules/ipld-dag-pb/src/util.js","original":{"line":12,"column":6}},{"name":"multihash","generated":{"line":13,"column":11},"source":"../node_modules/ipld-dag-pb/src/util.js","original":{"line":12,"column":11}},{"generated":{"line":13,"column":20},"source":"../node_modules/ipld-dag-pb/src/util.js","original":{"line":12,"column":2}},{"generated":{"line":13,"column":22},"source":"../node_modules/ipld-dag-pb/src/util.js","original":{"line":12,"column":22}},{"generated":{"line":14,"column":0},"source":"../node_modules/ipld-dag-pb/src/util.js","original":{"line":13,"column":4}},{"name":"callback","generated":{"line":14,"column":11},"source":"../node_modules/ipld-dag-pb/src/util.js","original":{"line":13,"column":11}},{"generated":{"line":14,"column":20},"source":"../node_modules/ipld-dag-pb/src/util.js","original":{"line":13,"column":20}},{"generated":{"line":14,"column":24},"source":"../node_modules/ipld-dag-pb/src/util.js","original":{"line":13,"column":11}},{"generated":{"line":14,"column":26},"source":"../node_modules/ipld-dag-pb/src/util.js","original":{"line":13,"column":26}},{"name":"CID","generated":{"line":14,"column":30},"source":"../node_modules/ipld-dag-pb/src/util.js","original":{"line":13,"column":30}},{"generated":{"line":14,"column":33},"source":"../node_modules/ipld-dag-pb/src/util.js","original":{"line":13,"column":26}},{"name":"node","generated":{"line":14,"column":34},"source":"../node_modules/ipld-dag-pb/src/util.js","original":{"line":13,"column":34}},{"name":"multihash","generated":{"line":14,"column":39},"source":"../node_modules/ipld-dag-pb/src/util.js","original":{"line":13,"column":39}},{"generated":{"line":14,"column":48},"source":"../node_modules/ipld-dag-pb/src/util.js","original":{"line":13,"column":26}},{"generated":{"line":14,"column":49},"source":"../node_modules/ipld-dag-pb/src/util.js","original":{"line":13,"column":11}},{"generated":{"line":14,"column":50},"source":"../node_modules/ipld-dag-pb/src/util.js","original":{"line":13,"column":4}},{"generated":{"line":15,"column":0},"source":"../node_modules/ipld-dag-pb/src/util.js","original":{"line":14,"column":3}},{"name":"callback","generated":{"line":16,"column":0},"source":"../node_modules/ipld-dag-pb/src/util.js","original":{"line":15,"column":2}},{"generated":{"line":16,"column":11},"source":"../node_modules/ipld-dag-pb/src/util.js","original":{"line":15,"column":11}},{"name":"Error","generated":{"line":16,"column":15},"source":"../node_modules/ipld-dag-pb/src/util.js","original":{"line":15,"column":15}},{"generated":{"line":16,"column":20},"source":"../node_modules/ipld-dag-pb/src/util.js","original":{"line":15,"column":11}},{"generated":{"line":16,"column":21},"source":"../node_modules/ipld-dag-pb/src/util.js","original":{"line":15,"column":21}},{"generated":{"line":16,"column":43},"source":"../node_modules/ipld-dag-pb/src/util.js","original":{"line":15,"column":11}},{"generated":{"line":16,"column":44},"source":"../node_modules/ipld-dag-pb/src/util.js","original":{"line":15,"column":2}},{"generated":{"line":17,"column":0},"source":"../node_modules/ipld-dag-pb/src/util.js","original":{"line":16,"column":1}},{"generated":{"line":19,"column":0},"source":"../node_modules/ipld-dag-pb/src/util.js","original":{"line":18,"column":0}},{"name":"serialize","generated":{"line":19,"column":9},"source":"../node_modules/ipld-dag-pb/src/util.js","original":{"line":18,"column":9}},{"generated":{"line":19,"column":18},"source":"../node_modules/ipld-dag-pb/src/util.js","original":{"line":18,"column":0}},{"name":"node","generated":{"line":19,"column":19},"source":"../node_modules/ipld-dag-pb/src/util.js","original":{"line":18,"column":20}},{"generated":{"line":19,"column":23},"source":"../node_modules/ipld-dag-pb/src/util.js","original":{"line":18,"column":0}},{"name":"callback","generated":{"line":19,"column":25},"source":"../node_modules/ipld-dag-pb/src/util.js","original":{"line":18,"column":26}},{"generated":{"line":19,"column":33},"source":"../node_modules/ipld-dag-pb/src/util.js","original":{"line":18,"column":0}},{"generated":{"line":19,"column":35},"source":"../node_modules/ipld-dag-pb/src/util.js","original":{"line":18,"column":36}},{"generated":{"line":20,"column":0},"source":"../node_modules/ipld-dag-pb/src/util.js","original":{"line":19,"column":2}},{"name":"serialized","generated":{"line":20,"column":6},"source":"../node_modules/ipld-dag-pb/src/util.js","original":{"line":19,"column":6}},{"generated":{"line":20,"column":25},"source":"../node_modules/ipld-dag-pb/src/util.js","original":{"line":19,"column":2}},{"generated":{"line":22,"column":0},"source":"../node_modules/ipld-dag-pb/src/util.js","original":{"line":21,"column":2}},{"generated":{"line":23,"column":0},"source":"../node_modules/ipld-dag-pb/src/util.js","original":{"line":22,"column":2}},{"generated":{"line":23,"column":6},"source":"../node_modules/ipld-dag-pb/src/util.js","original":{"line":22,"column":6}},{"name":"DAGNode","generated":{"line":23,"column":7},"source":"../node_modules/ipld-dag-pb/src/util.js","original":{"line":22,"column":7}},{"name":"isDAGNode","generated":{"line":23,"column":15},"source":"../node_modules/ipld-dag-pb/src/util.js","original":{"line":22,"column":15}},{"generated":{"line":23,"column":24},"source":"../node_modules/ipld-dag-pb/src/util.js","original":{"line":22,"column":7}},{"name":"node","generated":{"line":23,"column":25},"source":"../node_modules/ipld-dag-pb/src/util.js","original":{"line":22,"column":25}},{"generated":{"line":23,"column":29},"source":"../node_modules/ipld-dag-pb/src/util.js","original":{"line":22,"column":7}},{"generated":{"line":23,"column":30},"source":"../node_modules/ipld-dag-pb/src/util.js","original":{"line":22,"column":6}},{"name":"node","generated":{"line":23,"column":34},"source":"../node_modules/ipld-dag-pb/src/util.js","original":{"line":22,"column":34}},{"name":"links","generated":{"line":23,"column":39},"source":"../node_modules/ipld-dag-pb/src/util.js","original":{"line":22,"column":39}},{"generated":{"line":23,"column":44},"source":"../node_modules/ipld-dag-pb/src/util.js","original":{"line":22,"column":2}},{"generated":{"line":23,"column":46},"source":"../node_modules/ipld-dag-pb/src/util.js","original":{"line":22,"column":46}},{"name":"node","generated":{"line":24,"column":0},"source":"../node_modules/ipld-dag-pb/src/util.js","original":{"line":23,"column":4}},{"name":"links","generated":{"line":24,"column":9},"source":"../node_modules/ipld-dag-pb/src/util.js","original":{"line":23,"column":9}},{"generated":{"line":24,"column":14},"source":"../node_modules/ipld-dag-pb/src/util.js","original":{"line":23,"column":4}},{"name":"node","generated":{"line":24,"column":17},"source":"../node_modules/ipld-dag-pb/src/util.js","original":{"line":23,"column":17}},{"name":"links","generated":{"line":24,"column":22},"source":"../node_modules/ipld-dag-pb/src/util.js","original":{"line":23,"column":22}},{"generated":{"line":24,"column":27},"source":"../node_modules/ipld-dag-pb/src/util.js","original":{"line":23,"column":17}},{"name":"map","generated":{"line":24,"column":28},"source":"../node_modules/ipld-dag-pb/src/util.js","original":{"line":23,"column":28}},{"generated":{"line":24,"column":31},"source":"../node_modules/ipld-dag-pb/src/util.js","original":{"line":23,"column":17}},{"generated":{"line":24,"column":32},"source":"../node_modules/ipld-dag-pb/src/util.js","original":{"line":23,"column":32}},{"name":"link","generated":{"line":24,"column":42},"source":"../node_modules/ipld-dag-pb/src/util.js","original":{"line":23,"column":33}},{"generated":{"line":24,"column":46},"source":"../node_modules/ipld-dag-pb/src/util.js","original":{"line":23,"column":32}},{"generated":{"line":24,"column":48},"source":"../node_modules/ipld-dag-pb/src/util.js","original":{"line":23,"column":42}},{"generated":{"line":25,"column":0},"source":"../node_modules/ipld-dag-pb/src/util.js","original":{"line":24,"column":6}},{"name":"DAGLink","generated":{"line":25,"column":13},"source":"../node_modules/ipld-dag-pb/src/util.js","original":{"line":24,"column":13}},{"name":"isDAGLink","generated":{"line":25,"column":21},"source":"../node_modules/ipld-dag-pb/src/util.js","original":{"line":24,"column":21}},{"generated":{"line":25,"column":30},"source":"../node_modules/ipld-dag-pb/src/util.js","original":{"line":24,"column":13}},{"name":"link","generated":{"line":25,"column":31},"source":"../node_modules/ipld-dag-pb/src/util.js","original":{"line":24,"column":31}},{"generated":{"line":25,"column":35},"source":"../node_modules/ipld-dag-pb/src/util.js","original":{"line":24,"column":13}},{"name":"link","generated":{"line":25,"column":39},"source":"../node_modules/ipld-dag-pb/src/util.js","original":{"line":24,"column":39}},{"generated":{"line":25,"column":43},"source":"../node_modules/ipld-dag-pb/src/util.js","original":{"line":24,"column":13}},{"name":"DAGLink","generated":{"line":25,"column":46},"source":"../node_modules/ipld-dag-pb/src/util.js","original":{"line":24,"column":46}},{"name":"util","generated":{"line":25,"column":54},"source":"../node_modules/ipld-dag-pb/src/util.js","original":{"line":24,"column":54}},{"generated":{"line":25,"column":58},"source":"../node_modules/ipld-dag-pb/src/util.js","original":{"line":24,"column":46}},{"name":"createDagLinkFromB58EncodedHash","generated":{"line":25,"column":59},"source":"../node_modules/ipld-dag-pb/src/util.js","original":{"line":24,"column":59}},{"generated":{"line":25,"column":90},"source":"../node_modules/ipld-dag-pb/src/util.js","original":{"line":24,"column":46}},{"name":"link","generated":{"line":25,"column":91},"source":"../node_modules/ipld-dag-pb/src/util.js","original":{"line":24,"column":91}},{"generated":{"line":25,"column":95},"source":"../node_modules/ipld-dag-pb/src/util.js","original":{"line":24,"column":46}},{"generated":{"line":25,"column":96},"source":"../node_modules/ipld-dag-pb/src/util.js","original":{"line":24,"column":6}},{"generated":{"line":26,"column":0},"source":"../node_modules/ipld-dag-pb/src/util.js","original":{"line":25,"column":5}},{"generated":{"line":26,"column":5},"source":"../node_modules/ipld-dag-pb/src/util.js","original":{"line":23,"column":17}},{"generated":{"line":26,"column":6},"source":"../node_modules/ipld-dag-pb/src/util.js","original":{"line":23,"column":4}},{"generated":{"line":27,"column":0},"source":"../node_modules/ipld-dag-pb/src/util.js","original":{"line":26,"column":3}},{"generated":{"line":29,"column":0},"source":"../node_modules/ipld-dag-pb/src/util.js","original":{"line":28,"column":2}},{"generated":{"line":29,"column":6},"source":"../node_modules/ipld-dag-pb/src/util.js","original":{"line":28,"column":6}},{"name":"serialized","generated":{"line":30,"column":0},"source":"../node_modules/ipld-dag-pb/src/util.js","original":{"line":29,"column":4}},{"name":"proto","generated":{"line":30,"column":17},"source":"../node_modules/ipld-dag-pb/src/util.js","original":{"line":29,"column":17}},{"name":"PBNode","generated":{"line":30,"column":23},"source":"../node_modules/ipld-dag-pb/src/util.js","original":{"line":29,"column":23}},{"generated":{"line":30,"column":29},"source":"../node_modules/ipld-dag-pb/src/util.js","original":{"line":29,"column":17}},{"name":"encode","generated":{"line":30,"column":30},"source":"../node_modules/ipld-dag-pb/src/util.js","original":{"line":29,"column":30}},{"generated":{"line":30,"column":36},"source":"../node_modules/ipld-dag-pb/src/util.js","original":{"line":29,"column":17}},{"name":"toProtoBuf","generated":{"line":30,"column":37},"source":"../node_modules/ipld-dag-pb/src/util.js","original":{"line":29,"column":37}},{"name":"node","generated":{"line":30,"column":48},"source":"../node_modules/ipld-dag-pb/src/util.js","original":{"line":29,"column":48}},{"generated":{"line":30,"column":52},"source":"../node_modules/ipld-dag-pb/src/util.js","original":{"line":29,"column":37}},{"generated":{"line":30,"column":53},"source":"../node_modules/ipld-dag-pb/src/util.js","original":{"line":29,"column":17}},{"generated":{"line":30,"column":54},"source":"../node_modules/ipld-dag-pb/src/util.js","original":{"line":29,"column":4}},{"generated":{"line":31,"column":0},"source":"../node_modules/ipld-dag-pb/src/util.js","original":{"line":30,"column":3}},{"generated":{"line":31,"column":3},"source":"../node_modules/ipld-dag-pb/src/util.js","original":{"line":28,"column":2}},{"generated":{"line":31,"column":4},"source":"../node_modules/ipld-dag-pb/src/util.js","original":{"line":30,"column":4}},{"name":"err","generated":{"line":31,"column":11},"source":"../node_modules/ipld-dag-pb/src/util.js","original":{"line":30,"column":11}},{"generated":{"line":31,"column":14},"source":"../node_modules/ipld-dag-pb/src/util.js","original":{"line":30,"column":4}},{"generated":{"line":31,"column":16},"source":"../node_modules/ipld-dag-pb/src/util.js","original":{"line":30,"column":16}},{"generated":{"line":32,"column":0},"source":"../node_modules/ipld-dag-pb/src/util.js","original":{"line":31,"column":4}},{"name":"callback","generated":{"line":32,"column":11},"source":"../node_modules/ipld-dag-pb/src/util.js","original":{"line":31,"column":11}},{"name":"err","generated":{"line":32,"column":20},"source":"../node_modules/ipld-dag-pb/src/util.js","original":{"line":31,"column":20}},{"generated":{"line":32,"column":23},"source":"../node_modules/ipld-dag-pb/src/util.js","original":{"line":31,"column":11}},{"generated":{"line":32,"column":24},"source":"../node_modules/ipld-dag-pb/src/util.js","original":{"line":31,"column":4}},{"generated":{"line":33,"column":0},"source":"../node_modules/ipld-dag-pb/src/util.js","original":{"line":32,"column":3}},{"name":"callback","generated":{"line":35,"column":0},"source":"../node_modules/ipld-dag-pb/src/util.js","original":{"line":34,"column":2}},{"generated":{"line":35,"column":11},"source":"../node_modules/ipld-dag-pb/src/util.js","original":{"line":34,"column":11}},{"generated":{"line":35,"column":15},"source":"../node_modules/ipld-dag-pb/src/util.js","original":{"line":34,"column":2}},{"name":"serialized","generated":{"line":35,"column":17},"source":"../node_modules/ipld-dag-pb/src/util.js","original":{"line":34,"column":17}},{"generated":{"line":35,"column":27},"source":"../node_modules/ipld-dag-pb/src/util.js","original":{"line":34,"column":2}},{"generated":{"line":36,"column":0},"source":"../node_modules/ipld-dag-pb/src/util.js","original":{"line":35,"column":1}},{"generated":{"line":38,"column":0},"source":"../node_modules/ipld-dag-pb/src/util.js","original":{"line":37,"column":0}},{"name":"deserialize","generated":{"line":38,"column":9},"source":"../node_modules/ipld-dag-pb/src/util.js","original":{"line":37,"column":9}},{"generated":{"line":38,"column":20},"source":"../node_modules/ipld-dag-pb/src/util.js","original":{"line":37,"column":0}},{"name":"data","generated":{"line":38,"column":21},"source":"../node_modules/ipld-dag-pb/src/util.js","original":{"line":37,"column":22}},{"generated":{"line":38,"column":25},"source":"../node_modules/ipld-dag-pb/src/util.js","original":{"line":37,"column":0}},{"name":"callback","generated":{"line":38,"column":27},"source":"../node_modules/ipld-dag-pb/src/util.js","original":{"line":37,"column":28}},{"generated":{"line":38,"column":35},"source":"../node_modules/ipld-dag-pb/src/util.js","original":{"line":37,"column":0}},{"generated":{"line":38,"column":37},"source":"../node_modules/ipld-dag-pb/src/util.js","original":{"line":37,"column":38}},{"generated":{"line":39,"column":0},"source":"../node_modules/ipld-dag-pb/src/util.js","original":{"line":38,"column":2}},{"name":"pbn","generated":{"line":39,"column":6},"source":"../node_modules/ipld-dag-pb/src/util.js","original":{"line":38,"column":8}},{"name":"proto","generated":{"line":39,"column":12},"source":"../node_modules/ipld-dag-pb/src/util.js","original":{"line":38,"column":14}},{"name":"PBNode","generated":{"line":39,"column":18},"source":"../node_modules/ipld-dag-pb/src/util.js","original":{"line":38,"column":20}},{"generated":{"line":39,"column":24},"source":"../node_modules/ipld-dag-pb/src/util.js","original":{"line":38,"column":14}},{"name":"decode","generated":{"line":39,"column":25},"source":"../node_modules/ipld-dag-pb/src/util.js","original":{"line":38,"column":27}},{"generated":{"line":39,"column":31},"source":"../node_modules/ipld-dag-pb/src/util.js","original":{"line":38,"column":14}},{"name":"data","generated":{"line":39,"column":32},"source":"../node_modules/ipld-dag-pb/src/util.js","original":{"line":38,"column":34}},{"generated":{"line":39,"column":36},"source":"../node_modules/ipld-dag-pb/src/util.js","original":{"line":38,"column":14}},{"generated":{"line":39,"column":37},"source":"../node_modules/ipld-dag-pb/src/util.js","original":{"line":38,"column":2}},{"generated":{"line":41,"column":0},"source":"../node_modules/ipld-dag-pb/src/util.js","original":{"line":40,"column":2}},{"name":"links","generated":{"line":41,"column":6},"source":"../node_modules/ipld-dag-pb/src/util.js","original":{"line":40,"column":8}},{"name":"pbn","generated":{"line":41,"column":14},"source":"../node_modules/ipld-dag-pb/src/util.js","original":{"line":40,"column":16}},{"name":"Links","generated":{"line":41,"column":18},"source":"../node_modules/ipld-dag-pb/src/util.js","original":{"line":40,"column":20}},{"generated":{"line":41,"column":23},"source":"../node_modules/ipld-dag-pb/src/util.js","original":{"line":40,"column":16}},{"name":"map","generated":{"line":41,"column":24},"source":"../node_modules/ipld-dag-pb/src/util.js","original":{"line":40,"column":26}},{"generated":{"line":41,"column":27},"source":"../node_modules/ipld-dag-pb/src/util.js","original":{"line":40,"column":16}},{"generated":{"line":41,"column":28},"source":"../node_modules/ipld-dag-pb/src/util.js","original":{"line":40,"column":30}},{"name":"link","generated":{"line":41,"column":38},"source":"../node_modules/ipld-dag-pb/src/util.js","original":{"line":40,"column":31}},{"generated":{"line":41,"column":42},"source":"../node_modules/ipld-dag-pb/src/util.js","original":{"line":40,"column":30}},{"generated":{"line":41,"column":44},"source":"../node_modules/ipld-dag-pb/src/util.js","original":{"line":40,"column":40}},{"generated":{"line":42,"column":0},"source":"../node_modules/ipld-dag-pb/src/util.js","original":{"line":41,"column":4}},{"generated":{"line":42,"column":11},"source":"../node_modules/ipld-dag-pb/src/util.js","original":{"line":41,"column":11}},{"name":"DAGLink","generated":{"line":42,"column":15},"source":"../node_modules/ipld-dag-pb/src/util.js","original":{"line":41,"column":15}},{"generated":{"line":42,"column":22},"source":"../node_modules/ipld-dag-pb/src/util.js","original":{"line":41,"column":11}},{"name":"link","generated":{"line":42,"column":23},"source":"../node_modules/ipld-dag-pb/src/util.js","original":{"line":41,"column":23}},{"name":"Name","generated":{"line":42,"column":28},"source":"../node_modules/ipld-dag-pb/src/util.js","original":{"line":41,"column":28}},{"generated":{"line":42,"column":32},"source":"../node_modules/ipld-dag-pb/src/util.js","original":{"line":41,"column":11}},{"name":"link","generated":{"line":42,"column":34},"source":"../node_modules/ipld-dag-pb/src/util.js","original":{"line":41,"column":34}},{"name":"Tsize","generated":{"line":42,"column":39},"source":"../node_modules/ipld-dag-pb/src/util.js","original":{"line":41,"column":39}},{"generated":{"line":42,"column":44},"source":"../node_modules/ipld-dag-pb/src/util.js","original":{"line":41,"column":11}},{"name":"link","generated":{"line":42,"column":46},"source":"../node_modules/ipld-dag-pb/src/util.js","original":{"line":41,"column":46}},{"name":"Hash","generated":{"line":42,"column":51},"source":"../node_modules/ipld-dag-pb/src/util.js","original":{"line":41,"column":51}},{"generated":{"line":42,"column":55},"source":"../node_modules/ipld-dag-pb/src/util.js","original":{"line":41,"column":11}},{"generated":{"line":42,"column":56},"source":"../node_modules/ipld-dag-pb/src/util.js","original":{"line":41,"column":4}},{"generated":{"line":43,"column":0},"source":"../node_modules/ipld-dag-pb/src/util.js","original":{"line":42,"column":3}},{"generated":{"line":43,"column":3},"source":"../node_modules/ipld-dag-pb/src/util.js","original":{"line":40,"column":16}},{"generated":{"line":43,"column":4},"source":"../node_modules/ipld-dag-pb/src/util.js","original":{"line":40,"column":2}},{"generated":{"line":45,"column":0},"source":"../node_modules/ipld-dag-pb/src/util.js","original":{"line":44,"column":2}},{"name":"buf","generated":{"line":45,"column":6},"source":"../node_modules/ipld-dag-pb/src/util.js","original":{"line":44,"column":8}},{"name":"pbn","generated":{"line":45,"column":12},"source":"../node_modules/ipld-dag-pb/src/util.js","original":{"line":44,"column":14}},{"name":"Data","generated":{"line":45,"column":16},"source":"../node_modules/ipld-dag-pb/src/util.js","original":{"line":44,"column":18}},{"generated":{"line":45,"column":20},"source":"../node_modules/ipld-dag-pb/src/util.js","original":{"line":44,"column":14}},{"generated":{"line":45,"column":24},"source":"../node_modules/ipld-dag-pb/src/util.js","original":{"line":44,"column":26}},{"generated":{"line":45,"column":28},"source":"../node_modules/ipld-dag-pb/src/util.js","original":{"line":44,"column":14}},{"name":"Buffer","generated":{"line":45,"column":31},"source":"../node_modules/ipld-dag-pb/src/util.js","original":{"line":44,"column":33}},{"name":"alloc","generated":{"line":45,"column":38},"source":"../node_modules/ipld-dag-pb/src/util.js","original":{"line":44,"column":40}},{"generated":{"line":45,"column":43},"source":"../node_modules/ipld-dag-pb/src/util.js","original":{"line":44,"column":33}},{"generated":{"line":45,"column":44},"source":"../node_modules/ipld-dag-pb/src/util.js","original":{"line":44,"column":46}},{"generated":{"line":45,"column":45},"source":"../node_modules/ipld-dag-pb/src/util.js","original":{"line":44,"column":33}},{"generated":{"line":45,"column":46},"source":"../node_modules/ipld-dag-pb/src/util.js","original":{"line":44,"column":14}},{"name":"Buffer","generated":{"line":45,"column":49},"source":"../node_modules/ipld-dag-pb/src/util.js","original":{"line":44,"column":51}},{"name":"from","generated":{"line":45,"column":56},"source":"../node_modules/ipld-dag-pb/src/util.js","original":{"line":44,"column":58}},{"generated":{"line":45,"column":60},"source":"../node_modules/ipld-dag-pb/src/util.js","original":{"line":44,"column":51}},{"name":"pbn","generated":{"line":45,"column":61},"source":"../node_modules/ipld-dag-pb/src/util.js","original":{"line":44,"column":63}},{"name":"Data","generated":{"line":45,"column":65},"source":"../node_modules/ipld-dag-pb/src/util.js","original":{"line":44,"column":67}},{"generated":{"line":45,"column":69},"source":"../node_modules/ipld-dag-pb/src/util.js","original":{"line":44,"column":51}},{"generated":{"line":45,"column":70},"source":"../node_modules/ipld-dag-pb/src/util.js","original":{"line":44,"column":2}},{"name":"DAGNode","generated":{"line":47,"column":0},"source":"../node_modules/ipld-dag-pb/src/util.js","original":{"line":46,"column":2}},{"name":"create","generated":{"line":47,"column":10},"source":"../node_modules/ipld-dag-pb/src/util.js","original":{"line":46,"column":10}},{"generated":{"line":47,"column":16},"source":"../node_modules/ipld-dag-pb/src/util.js","original":{"line":46,"column":2}},{"name":"buf","generated":{"line":47,"column":17},"source":"../node_modules/ipld-dag-pb/src/util.js","original":{"line":46,"column":17}},{"generated":{"line":47,"column":20},"source":"../node_modules/ipld-dag-pb/src/util.js","original":{"line":46,"column":2}},{"name":"links","generated":{"line":47,"column":22},"source":"../node_modules/ipld-dag-pb/src/util.js","original":{"line":46,"column":22}},{"generated":{"line":47,"column":27},"source":"../node_modules/ipld-dag-pb/src/util.js","original":{"line":46,"column":2}},{"name":"callback","generated":{"line":47,"column":29},"source":"../node_modules/ipld-dag-pb/src/util.js","original":{"line":46,"column":29}},{"generated":{"line":47,"column":37},"source":"../node_modules/ipld-dag-pb/src/util.js","original":{"line":46,"column":2}},{"generated":{"line":48,"column":0},"source":"../node_modules/ipld-dag-pb/src/util.js","original":{"line":47,"column":1}},{"generated":{"line":50,"column":0},"source":"../node_modules/ipld-dag-pb/src/util.js","original":{"line":49,"column":0}},{"name":"toProtoBuf","generated":{"line":50,"column":9},"source":"../node_modules/ipld-dag-pb/src/util.js","original":{"line":49,"column":9}},{"generated":{"line":50,"column":19},"source":"../node_modules/ipld-dag-pb/src/util.js","original":{"line":49,"column":0}},{"name":"node","generated":{"line":50,"column":20},"source":"../node_modules/ipld-dag-pb/src/util.js","original":{"line":49,"column":21}},{"generated":{"line":50,"column":24},"source":"../node_modules/ipld-dag-pb/src/util.js","original":{"line":49,"column":0}},{"generated":{"line":50,"column":26},"source":"../node_modules/ipld-dag-pb/src/util.js","original":{"line":49,"column":27}},{"generated":{"line":51,"column":0},"source":"../node_modules/ipld-dag-pb/src/util.js","original":{"line":50,"column":2}},{"name":"pbn","generated":{"line":51,"column":6},"source":"../node_modules/ipld-dag-pb/src/util.js","original":{"line":50,"column":8}},{"generated":{"line":51,"column":12},"source":"../node_modules/ipld-dag-pb/src/util.js","original":{"line":50,"column":14}},{"generated":{"line":51,"column":14},"source":"../node_modules/ipld-dag-pb/src/util.js","original":{"line":50,"column":2}},{"generated":{"line":53,"column":0},"source":"../node_modules/ipld-dag-pb/src/util.js","original":{"line":52,"column":2}},{"name":"node","generated":{"line":53,"column":6},"source":"../node_modules/ipld-dag-pb/src/util.js","original":{"line":52,"column":6}},{"name":"data","generated":{"line":53,"column":11},"source":"../node_modules/ipld-dag-pb/src/util.js","original":{"line":52,"column":11}},{"generated":{"line":53,"column":15},"source":"../node_modules/ipld-dag-pb/src/util.js","original":{"line":52,"column":6}},{"name":"node","generated":{"line":53,"column":19},"source":"../node_modules/ipld-dag-pb/src/util.js","original":{"line":52,"column":19}},{"name":"data","generated":{"line":53,"column":24},"source":"../node_modules/ipld-dag-pb/src/util.js","original":{"line":52,"column":24}},{"generated":{"line":53,"column":28},"source":"../node_modules/ipld-dag-pb/src/util.js","original":{"line":52,"column":19}},{"name":"length","generated":{"line":53,"column":29},"source":"../node_modules/ipld-dag-pb/src/util.js","original":{"line":52,"column":29}},{"generated":{"line":53,"column":35},"source":"../node_modules/ipld-dag-pb/src/util.js","original":{"line":52,"column":19}},{"generated":{"line":53,"column":38},"source":"../node_modules/ipld-dag-pb/src/util.js","original":{"line":52,"column":38}},{"generated":{"line":53,"column":39},"source":"../node_modules/ipld-dag-pb/src/util.js","original":{"line":52,"column":2}},{"generated":{"line":53,"column":41},"source":"../node_modules/ipld-dag-pb/src/util.js","original":{"line":52,"column":41}},{"name":"pbn","generated":{"line":54,"column":0},"source":"../node_modules/ipld-dag-pb/src/util.js","original":{"line":53,"column":4}},{"name":"Data","generated":{"line":54,"column":8},"source":"../node_modules/ipld-dag-pb/src/util.js","original":{"line":53,"column":8}},{"generated":{"line":54,"column":12},"source":"../node_modules/ipld-dag-pb/src/util.js","original":{"line":53,"column":4}},{"name":"node","generated":{"line":54,"column":15},"source":"../node_modules/ipld-dag-pb/src/util.js","original":{"line":53,"column":15}},{"name":"data","generated":{"line":54,"column":20},"source":"../node_modules/ipld-dag-pb/src/util.js","original":{"line":53,"column":20}},{"generated":{"line":54,"column":24},"source":"../node_modules/ipld-dag-pb/src/util.js","original":{"line":53,"column":4}},{"generated":{"line":55,"column":0},"source":"../node_modules/ipld-dag-pb/src/util.js","original":{"line":54,"column":3}},{"generated":{"line":55,"column":3},"source":"../node_modules/ipld-dag-pb/src/util.js","original":{"line":52,"column":2}},{"generated":{"line":55,"column":9},"source":"../node_modules/ipld-dag-pb/src/util.js","original":{"line":54,"column":9}},{"generated":{"line":56,"column":0},"source":"../node_modules/ipld-dag-pb/src/util.js","original":{"line":55,"column":4}},{"name":"pbn","generated":{"line":57,"column":0},"source":"../node_modules/ipld-dag-pb/src/util.js","original":{"line":56,"column":4}},{"name":"Data","generated":{"line":57,"column":8},"source":"../node_modules/ipld-dag-pb/src/util.js","original":{"line":56,"column":8}},{"generated":{"line":57,"column":12},"source":"../node_modules/ipld-dag-pb/src/util.js","original":{"line":56,"column":4}},{"generated":{"line":57,"column":15},"source":"../node_modules/ipld-dag-pb/src/util.js","original":{"line":56,"column":15}},{"generated":{"line":57,"column":19},"source":"../node_modules/ipld-dag-pb/src/util.js","original":{"line":56,"column":4}},{"generated":{"line":58,"column":0},"source":"../node_modules/ipld-dag-pb/src/util.js","original":{"line":57,"column":3}},{"generated":{"line":60,"column":0},"source":"../node_modules/ipld-dag-pb/src/util.js","original":{"line":59,"column":2}},{"name":"node","generated":{"line":60,"column":6},"source":"../node_modules/ipld-dag-pb/src/util.js","original":{"line":59,"column":6}},{"name":"links","generated":{"line":60,"column":11},"source":"../node_modules/ipld-dag-pb/src/util.js","original":{"line":59,"column":11}},{"generated":{"line":60,"column":16},"source":"../node_modules/ipld-dag-pb/src/util.js","original":{"line":59,"column":6}},{"name":"node","generated":{"line":60,"column":20},"source":"../node_modules/ipld-dag-pb/src/util.js","original":{"line":59,"column":20}},{"name":"links","generated":{"line":60,"column":25},"source":"../node_modules/ipld-dag-pb/src/util.js","original":{"line":59,"column":25}},{"generated":{"line":60,"column":30},"source":"../node_modules/ipld-dag-pb/src/util.js","original":{"line":59,"column":20}},{"name":"length","generated":{"line":60,"column":31},"source":"../node_modules/ipld-dag-pb/src/util.js","original":{"line":59,"column":31}},{"generated":{"line":60,"column":37},"source":"../node_modules/ipld-dag-pb/src/util.js","original":{"line":59,"column":20}},{"generated":{"line":60,"column":40},"source":"../node_modules/ipld-dag-pb/src/util.js","original":{"line":59,"column":40}},{"generated":{"line":60,"column":41},"source":"../node_modules/ipld-dag-pb/src/util.js","original":{"line":59,"column":2}},{"generated":{"line":60,"column":43},"source":"../node_modules/ipld-dag-pb/src/util.js","original":{"line":59,"column":43}},{"name":"pbn","generated":{"line":61,"column":0},"source":"../node_modules/ipld-dag-pb/src/util.js","original":{"line":60,"column":4}},{"name":"Links","generated":{"line":61,"column":8},"source":"../node_modules/ipld-dag-pb/src/util.js","original":{"line":60,"column":8}},{"generated":{"line":61,"column":13},"source":"../node_modules/ipld-dag-pb/src/util.js","original":{"line":60,"column":4}},{"name":"node","generated":{"line":61,"column":16},"source":"../node_modules/ipld-dag-pb/src/util.js","original":{"line":60,"column":16}},{"name":"links","generated":{"line":61,"column":21},"source":"../node_modules/ipld-dag-pb/src/util.js","original":{"line":60,"column":21}},{"generated":{"line":61,"column":26},"source":"../node_modules/ipld-dag-pb/src/util.js","original":{"line":60,"column":16}},{"name":"map","generated":{"line":61,"column":27},"source":"../node_modules/ipld-dag-pb/src/util.js","original":{"line":60,"column":27}},{"generated":{"line":61,"column":30},"source":"../node_modules/ipld-dag-pb/src/util.js","original":{"line":60,"column":16}},{"generated":{"line":61,"column":31},"source":"../node_modules/ipld-dag-pb/src/util.js","original":{"line":60,"column":31}},{"name":"link","generated":{"line":61,"column":41},"source":"../node_modules/ipld-dag-pb/src/util.js","original":{"line":60,"column":32}},{"generated":{"line":61,"column":45},"source":"../node_modules/ipld-dag-pb/src/util.js","original":{"line":60,"column":31}},{"generated":{"line":61,"column":47},"source":"../node_modules/ipld-dag-pb/src/util.js","original":{"line":60,"column":41}},{"generated":{"line":62,"column":0},"source":"../node_modules/ipld-dag-pb/src/util.js","original":{"line":61,"column":6}},{"generated":{"line":62,"column":13},"source":"../node_modules/ipld-dag-pb/src/util.js","original":{"line":61,"column":13}},{"name":"Hash","generated":{"line":63,"column":0},"source":"../node_modules/ipld-dag-pb/src/util.js","original":{"line":62,"column":8}},{"name":"link","generated":{"line":63,"column":14},"source":"../node_modules/ipld-dag-pb/src/util.js","original":{"line":62,"column":14}},{"name":"multihash","generated":{"line":63,"column":19},"source":"../node_modules/ipld-dag-pb/src/util.js","original":{"line":62,"column":19}},{"generated":{"line":63,"column":28},"source":"../node_modules/ipld-dag-pb/src/util.js","original":{"line":61,"column":13}},{"name":"Name","generated":{"line":64,"column":0},"source":"../node_modules/ipld-dag-pb/src/util.js","original":{"line":63,"column":8}},{"name":"link","generated":{"line":64,"column":14},"source":"../node_modules/ipld-dag-pb/src/util.js","original":{"line":63,"column":14}},{"name":"name","generated":{"line":64,"column":19},"source":"../node_modules/ipld-dag-pb/src/util.js","original":{"line":63,"column":19}},{"generated":{"line":64,"column":23},"source":"../node_modules/ipld-dag-pb/src/util.js","original":{"line":61,"column":13}},{"name":"Tsize","generated":{"line":65,"column":0},"source":"../node_modules/ipld-dag-pb/src/util.js","original":{"line":64,"column":8}},{"name":"link","generated":{"line":65,"column":15},"source":"../node_modules/ipld-dag-pb/src/util.js","original":{"line":64,"column":15}},{"name":"size","generated":{"line":65,"column":20},"source":"../node_modules/ipld-dag-pb/src/util.js","original":{"line":64,"column":20}},{"generated":{"line":66,"column":0},"source":"../node_modules/ipld-dag-pb/src/util.js","original":{"line":61,"column":13}},{"generated":{"line":66,"column":7},"source":"../node_modules/ipld-dag-pb/src/util.js","original":{"line":61,"column":6}},{"generated":{"line":67,"column":0},"source":"../node_modules/ipld-dag-pb/src/util.js","original":{"line":66,"column":5}},{"generated":{"line":67,"column":5},"source":"../node_modules/ipld-dag-pb/src/util.js","original":{"line":60,"column":16}},{"generated":{"line":67,"column":6},"source":"../node_modules/ipld-dag-pb/src/util.js","original":{"line":60,"column":4}},{"generated":{"line":68,"column":0},"source":"../node_modules/ipld-dag-pb/src/util.js","original":{"line":67,"column":3}},{"generated":{"line":68,"column":3},"source":"../node_modules/ipld-dag-pb/src/util.js","original":{"line":59,"column":2}},{"generated":{"line":68,"column":9},"source":"../node_modules/ipld-dag-pb/src/util.js","original":{"line":67,"column":9}},{"name":"pbn","generated":{"line":69,"column":0},"source":"../node_modules/ipld-dag-pb/src/util.js","original":{"line":68,"column":4}},{"name":"Links","generated":{"line":69,"column":8},"source":"../node_modules/ipld-dag-pb/src/util.js","original":{"line":68,"column":8}},{"generated":{"line":69,"column":13},"source":"../node_modules/ipld-dag-pb/src/util.js","original":{"line":68,"column":4}},{"generated":{"line":69,"column":16},"source":"../node_modules/ipld-dag-pb/src/util.js","original":{"line":68,"column":16}},{"generated":{"line":69,"column":20},"source":"../node_modules/ipld-dag-pb/src/util.js","original":{"line":68,"column":4}},{"generated":{"line":70,"column":0},"source":"../node_modules/ipld-dag-pb/src/util.js","original":{"line":69,"column":3}},{"generated":{"line":72,"column":0},"source":"../node_modules/ipld-dag-pb/src/util.js","original":{"line":71,"column":2}},{"name":"pbn","generated":{"line":72,"column":9},"source":"../node_modules/ipld-dag-pb/src/util.js","original":{"line":71,"column":9}},{"generated":{"line":72,"column":12},"source":"../node_modules/ipld-dag-pb/src/util.js","original":{"line":71,"column":2}},{"generated":{"line":73,"column":0},"source":"../node_modules/ipld-dag-pb/src/util.js","original":{"line":72,"column":1}},{"name":"exports","generated":{"line":75,"column":0},"source":"../node_modules/ipld-dag-pb/src/util.js","original":{"line":74,"column":0}},{"name":"serialize","generated":{"line":75,"column":8},"source":"../node_modules/ipld-dag-pb/src/util.js","original":{"line":74,"column":8}},{"generated":{"line":75,"column":17},"source":"../node_modules/ipld-dag-pb/src/util.js","original":{"line":74,"column":0}},{"name":"serialize","generated":{"line":75,"column":20},"source":"../node_modules/ipld-dag-pb/src/util.js","original":{"line":74,"column":20}},{"generated":{"line":75,"column":29},"source":"../node_modules/ipld-dag-pb/src/util.js","original":{"line":74,"column":0}},{"name":"exports","generated":{"line":76,"column":0},"source":"../node_modules/ipld-dag-pb/src/util.js","original":{"line":75,"column":0}},{"name":"deserialize","generated":{"line":76,"column":8},"source":"../node_modules/ipld-dag-pb/src/util.js","original":{"line":75,"column":8}},{"generated":{"line":76,"column":19},"source":"../node_modules/ipld-dag-pb/src/util.js","original":{"line":75,"column":0}},{"name":"deserialize","generated":{"line":76,"column":22},"source":"../node_modules/ipld-dag-pb/src/util.js","original":{"line":75,"column":22}},{"generated":{"line":76,"column":33},"source":"../node_modules/ipld-dag-pb/src/util.js","original":{"line":75,"column":0}},{"name":"exports","generated":{"line":77,"column":0},"source":"../node_modules/ipld-dag-pb/src/util.js","original":{"line":76,"column":0}},{"name":"cid","generated":{"line":77,"column":8},"source":"../node_modules/ipld-dag-pb/src/util.js","original":{"line":76,"column":8}},{"generated":{"line":77,"column":11},"source":"../node_modules/ipld-dag-pb/src/util.js","original":{"line":76,"column":0}},{"name":"cid","generated":{"line":77,"column":14},"source":"../node_modules/ipld-dag-pb/src/util.js","original":{"line":76,"column":14}},{"generated":{"line":77,"column":17},"source":"../node_modules/ipld-dag-pb/src/util.js","original":{"line":76,"column":0}}],"sources":{"../node_modules/ipld-dag-pb/src/util.js":"'use strict'\n\nconst CID = require('cids')\nconst protons = require('protons')\nconst proto = protons(require('./dag.proto.js'))\nconst DAGLink = require('./dag-link')\nconst DAGNode = require('./dag-node')\n\nexports = module.exports\n\nfunction cid (node, callback) {\n  if (node.multihash) {\n    return callback(null, new CID(node.multihash))\n  }\n  callback(new Error('not valid dagPB node'))\n}\n\nfunction serialize (node, callback) {\n  let serialized\n\n  // If the node is not an instance of a DAGNode, the link.hash might be a Base58 encoded string; decode it\n  if (!DAGNode.isDAGNode(node) && node.links) {\n    node.links = node.links.map((link) => {\n      return DAGLink.isDAGLink(link) ? link : DAGLink.util.createDagLinkFromB58EncodedHash(link)\n    })\n  }\n\n  try {\n    serialized = proto.PBNode.encode(toProtoBuf(node))\n  } catch (err) {\n    return callback(err)\n  }\n\n  callback(null, serialized)\n}\n\nfunction deserialize (data, callback) {\n  const pbn = proto.PBNode.decode(data)\n\n  const links = pbn.Links.map((link) => {\n    return new DAGLink(link.Name, link.Tsize, link.Hash)\n  })\n\n  const buf = pbn.Data == null ? Buffer.alloc(0) : Buffer.from(pbn.Data)\n\n  DAGNode.create(buf, links, callback)\n}\n\nfunction toProtoBuf (node) {\n  const pbn = {}\n\n  if (node.data && node.data.length > 0) {\n    pbn.Data = node.data\n  } else {\n    // NOTE: this has to be null in order to match go-ipfs serialization `null !== new Buffer(0)`\n    pbn.Data = null\n  }\n\n  if (node.links && node.links.length > 0) {\n    pbn.Links = node.links.map((link) => {\n      return {\n        Hash: link.multihash,\n        Name: link.name,\n        Tsize: link.size\n      }\n    })\n  } else {\n    pbn.Links = null\n  }\n\n  return pbn\n}\n\nexports.serialize = serialize\nexports.deserialize = deserialize\nexports.cid = cid\n"},"lineCount":null}},"hash":"eca4db71e19f2f8630a35e9df70368f8","cacheData":{"env":{}}}